{"ec2osqhFf6JoKlMDIZzlvQ==":"cj's%20sweets%20website%20cover-1400x933.png","nS3vhPTp3jG5SZ2WD/wC4w==":"taylor-rooney-776853-unsplash-2000x2667.jpg","0hexfTnqpooWHcRqym0tWA==":"cj's%20sweets!-192x192.png","wlluU+2BzQehMWKVRZdIzA==":"cj's%20sweets!-122x122.png","5HjmwzJGaxVQMbe8iAsmIg==":"jonathan-j-castellon-1285733-unsplash-2000x1333.jpg","00zZUyXhpQoaC0uKo25qvA==":"product1.jpg","mIIbxW0r7dEZSbMPwcoYdg==":"background2.jpg","FEk/8dYsXzufnRQa/q8Gqw==":"cjs_sweet_photo_shop_express_photo-1368x992.jpg","kOdcxx5Ydt1Lwi3uEuqX3w==":"cjs_sweet_photo_shop_express_photo-2-1368x992.jpg","OvoICUwW3R/XJEHSspxPyg==":"cj's%20sweets%20website%20cover%202-1400x933.png","CBuj555tKYcb8ZaXqu54xA==":"mbr-1920x883.jpg","E9bmuE56B+z8c5S1ez7jww==":"cj's%20sweets%20website%20cover%203-1400x933.png","MScH/Ftoxz1gjJOxP9lesA==":"cj's%20sweets%20website%20cover%204-1400x933.png","D4yPlRp8Uzjj0mO3zyopmw==":"cjs_sweet_photo_shop_express_mothers_day_package-907x1467.jpg","uWutM1qENkc/wJPjvL1PJA==":"cjs_sweet_photo_shop_express_graduation_package-851x1467.jpg","HrYfIIFxtcPshwkEbdcgpA==":"cjs_sweet_photo_shop_express_spa_package-952x1394.jpg","6slwNhtz49jqbTJI35ac2w==":"hersheys_cjs_sweets-952x1279.jpg","FwwcM0WNpTIMDf2HyXqtgw==":"kit_kat_cjs_sweets-2-952x1337.jpg","9doPGazyZh/CuPT1rj4cEg==":"reseeses_cjs_sweets-2-901x1600.jpg","hzWwTRHw+bhn5t2RCl2rbg==":"hersheys_cjs_sweets-1191x1600.jpg"}